raddinian_calendar/__init__.py
raddinian_calendar/converter.py
raddinian_calendar-1.0.2.dist-info/LICENSE
raddinian_calendar-1.0.2.dist-info/METADATA
raddinian_calendar-1.0.2.dist-info/WHEEL
raddinian_calendar-1.0.2.dist-info/top_level.txt
raddinian_calendar-1.0.2.dist-info/RECORD
