Metadata-Version: 2.2
Name: raddinian-calendar
Version: 1.0.2
Summary: A module to convert between Raddinian and Gregorian calendars.
Home-page: https://github.com/violetradd/raddinian-calendar
Author: Violet Radd
Author-email: metatronzero199@gmail.com
Classifier: Programming Language :: Python :: 3
Classifier: License :: OSI Approved :: MIT License
Classifier: Operating System :: OS Independent
Requires-Python: >=3.6
License-File: LICENSE
Dynamic: author
Dynamic: author-email
Dynamic: classifier
Dynamic: home-page
Dynamic: requires-python
Dynamic: summary
